perpl/__init__.py
perpl/relative_positions.py
perpl/rot_2d_symm_fit.py
perpl/io/__init__.py
perpl/io/plotting.py
perpl/io/reports.py
perpl/io/utils.py
perpl/modelling/__init__.py
perpl/modelling/background_models.py
perpl/modelling/centriole_analysis.py
perpl/modelling/dna_paint_data_fitting.py
perpl/modelling/linearrepeatmodels.py
perpl/modelling/modelling_general.py
perpl/modelling/models_2d_distances_normalised.py
perpl/modelling/polyhedramodelling.py
perpl/modelling/two_layer_fitting.py
perpl/modelling/zdisk_modelling.py
perpl/modelling/zdisk_plots.py
perpl/statistics/__init.py__
perpl/statistics/modelstats.py
perpl-1.1.0.dist-info/licenses/license.md
perpl-1.1.0.dist-info/METADATA
perpl-1.1.0.dist-info/WHEEL
perpl-1.1.0.dist-info/entry_points.txt
perpl-1.1.0.dist-info/top_level.txt
perpl-1.1.0.dist-info/RECORD
