Metadata-Version: 2.4
Name: perpl
Version: 1.1.0
Summary: A package for point pattern analysis: Pattern Extraction from Relative Positions of Localisations
Author-email: Alistair Curd <a.curd@leeds.ac.uk>
Project-URL: Homepage, https://github.com/AlistairCurd/PERPL-Python3
Project-URL: Issues, https://github.com/AlistairCurd/PERPL-Python3/issues
Classifier: Programming Language :: Python :: 3
Classifier: License :: OSI Approved :: Apache Software License
Classifier: Operating System :: OS Independent
Requires-Python: >=3.11
License-File: license.md
Requires-Dist: numpy~=1.26
Requires-Dist: scipy~=1.12
Requires-Dist: numdifftools~=0.9
Requires-Dist: pandas~=2.2
Requires-Dist: matplotlib~=3.8
Requires-Dist: scikit-image~=0.22
Requires-Dist: jupyter~=1.0
Requires-Dist: jupytext~=1.16
Dynamic: license-file
